[
    {
        "Brand": "Geely",
        "Model": "CK",
        "Articul": 1400618180,
        "Part_Name": "Амортизатор задний правый",
        "Description": "Амортизатор задний правый",
        "Price": 21.4,
        "Img": "https://dummyimage.com/640x480/2a2a2a/ffffff&text=%D0%A4%D0%BE%D1%82%D0%BE+%D0%BE%D1%87%D1%96%D0%BA%D1%83%D1%94%D1%82%D1%8C%D1%81%D1%8F",
        "In_stock": "+",
        "Country": "Китай",
        "Quantity": 3
    },
    {
        "Brand": "Geely",
        "Model": "CK",
        "Articul": 1400516180,
        "Part_Name": "Амортизатор передний левый",
        "Description": "Амортизатор передний левый",
        "Price": 20,
        "Img": "https://dummyimage.com/640x480/2a2a2a/ffffff&text=%D0%A4%D0%BE%D1%82%D0%BE+%D0%BE%D1%87%D1%96%D0%BA%D1%83%D1%94%D1%82%D1%8C%D1%81%D1%8F",
        "In_stock": "+",
        "Country": "Китай",
        "Quantity": 5
    },
    {
        "Brand": "Geely",
        "Model": "CK",
        "Articul": 1400518180,
        "Part_Name": "Амортизатор передний правый",
        "Description": "Амортизатор передний правый",
        "Price": 20,
        "Img": "https://dummyimage.com/640x480/2a2a2a/ffffff&text=%D0%A4%D0%BE%D1%82%D0%BE+%D0%BE%D1%87%D1%96%D0%BA%D1%83%D1%94%D1%82%D1%8C%D1%81%D1%8F",
        "In_stock": "+",
        "Country": "Китай",
        "Quantity": 19
    },
    {
        "Brand": "Geely",
        "Model": "CK",
        "Articul": 1802542180,
        "Part_Name": "Брызговик задний левый  ",
        "Description": "Брызговик задний левый  ",
        "Price": 1.5,
        "Img": "https://dummyimage.com/640x480/2a2a2a/ffffff&text=%D0%A4%D0%BE%D1%82%D0%BE+%D0%BE%D1%87%D1%96%D0%BA%D1%83%D1%94%D1%82%D1%8C%D1%81%D1%8F",
        "In_stock": "+",
        "Country": "Китай",
        "Quantity": 9
    },
    {
        "Brand": "Geely",
        "Model": "CK",
        "Articul": 3160121101,
        "Part_Name": "Вилка сцепления СК МК",
        "Description": "Вилка сцепления СК МК",
        "Price": 3.2142857142857144,
        "Img": "https://dummyimage.com/640x480/2a2a2a/ffffff&text=%D0%A4%D0%BE%D1%82%D0%BE+%D0%BE%D1%87%D1%96%D0%BA%D1%83%D1%94%D1%82%D1%8C%D1%81%D1%8F",
        "In_stock": "+",
        "Country": "Китай",
        "Quantity": 5
    },
    {
        "Brand": "Geely",
        "Model": "CK",
        "Articul": 1602192180,
        "Part_Name": "Вентилятор охлаждения кондиционера (правый) (1016003507)",
        "Description": "Вентилятор охлаждения кондиционера (правый) (1016003507)",
        "Price": 21.4,
        "Img": "https://dummyimage.com/640x480/2a2a2a/ffffff&text=%D0%A4%D0%BE%D1%82%D0%BE+%D0%BE%D1%87%D1%96%D0%BA%D1%83%D1%94%D1%82%D1%8C%D1%81%D1%8F",
        "In_stock": "+",
        "Country": "Китай",
        "Quantity": 3
    },
    {
        "Brand": "Geely",
        "Model": "CK",
        "Articul": "E020301401",
        "Part_Name": "Вкладыш коленвала std",
        "Description": "Вкладыш коленвала std",
        "Price": 5,
        "Img": "https://dummyimage.com/640x480/2a2a2a/ffffff&text=%D0%A4%D0%BE%D1%82%D0%BE+%D0%BE%D1%87%D1%96%D0%BA%D1%83%D1%94%D1%82%D1%8C%D1%81%D1%8F",
        "In_stock": "+",
        "Country": "Китай",
        "Quantity": 2
    },
    {
        "Brand": "Geely",
        "Model": "CK",
        "Articul": 1064020005,
        "Part_Name": "Втулка заднего стабилизатора",
        "Description": "Втулка заднего стабилизатора",
        "Price": 0.35714285714285715,
        "Img": "https://dummyimage.com/640x480/2a2a2a/ffffff&text=%D0%A4%D0%BE%D1%82%D0%BE+%D0%BE%D1%87%D1%96%D0%BA%D1%83%D1%94%D1%82%D1%8C%D1%81%D1%8F",
        "In_stock": "+",
        "Country": "Китай",
        "Quantity": 23
    },
    {
        "Brand": "Geely",
        "Model": "CK",
        "Articul": "E020600005",
        "Part_Name": "Датчик давления масла CK/MK/FC 1106013220",
        "Description": "Датчик давления масла CK/MK/FC 1106013220",
        "Price": 1.5,
        "Img": "https://dummyimage.com/640x480/2a2a2a/ffffff&text=%D0%A4%D0%BE%D1%82%D0%BE+%D0%BE%D1%87%D1%96%D0%BA%D1%83%D1%94%D1%82%D1%8C%D1%81%D1%8F",
        "In_stock": "+",
        "Country": "Китай",
        "Quantity": 4
    },
    {
        "Brand": "Geely",
        "Model": "CK",
        "Articul": "E150070005",
        "Part_Name": "Датчик положения дроссельной заслонки",
        "Description": "Датчик положения дроссельной заслонки",
        "Price": 3.39,
        "Img": "https://dummyimage.com/640x480/2a2a2a/ffffff&text=%D0%A4%D0%BE%D1%82%D0%BE+%D0%BE%D1%87%D1%96%D0%BA%D1%83%D1%94%D1%82%D1%8C%D1%81%D1%8F",
        "In_stock": "+",
        "Country": "Китай",
        "Quantity": 4
    },
    {
        "Brand": "Geely",
        "Model": "CK",
        "Articul": 1700201180,
        "Part_Name": "Датчик скорости",
        "Description": "Датчик скорости",
        "Price": 4,
        "Img": "https://dummyimage.com/640x480/2a2a2a/ffffff&text=%D0%A4%D0%BE%D1%82%D0%BE+%D0%BE%D1%87%D1%96%D0%BA%D1%83%D1%94%D1%82%D1%8C%D1%81%D1%8F",
        "In_stock": "+",
        "Country": "Китай",
        "Quantity": 2
    },
    {
        "Brand": "Geely",
        "Model": "CK",
        "Articul": "E150050005",
        "Part_Name": "Датчик температуры охлаждающей жидкости",
        "Description": "Датчик температуры охлаждающей жидкости",
        "Price": 2,
        "Img": "https://dummyimage.com/640x480/2a2a2a/ffffff&text=%D0%A4%D0%BE%D1%82%D0%BE+%D0%BE%D1%87%D1%96%D0%BA%D1%83%D1%94%D1%82%D1%8C%D1%81%D1%8F",
        "In_stock": "+",
        "Country": "Китай",
        "Quantity": 3
    },
    {
        "Brand": "Geely",
        "Model": "CK",
        "Articul": "E582001372",
        "Part_Name": "Датчик холостого хода",
        "Description": "Датчик холостого хода",
        "Price": 10,
        "Img": "https://dummyimage.com/640x480/2a2a2a/ffffff&text=%D0%A4%D0%BE%D1%82%D0%BE+%D0%BE%D1%87%D1%96%D0%BA%D1%83%D1%94%D1%82%D1%8C%D1%81%D1%8F",
        "In_stock": "+",
        "Country": "Китай",
        "Quantity": 1
    },
    {
        "Brand": "Geely",
        "Model": "CK",
        "Articul": "E100200005",
        "Part_Name": "Диск сцепления",
        "Description": "Диск сцепления",
        "Price": 10,
        "Img": "https://dummyimage.com/640x480/2a2a2a/ffffff&text=%D0%A4%D0%BE%D1%82%D0%BE+%D0%BE%D1%87%D1%96%D0%BA%D1%83%D1%94%D1%82%D1%8C%D1%81%D1%8F",
        "In_stock": "+",
        "Country": "Китай",
        "Quantity": 3
    },
    {
        "Brand": "Geely",
        "Model": "CK",
        "Articul": "E010000501",
        "Part_Name": "Клапан впускной ",
        "Description": "Клапан впускной ",
        "Price": 1,
        "Img": "https://dummyimage.com/640x480/2a2a2a/ffffff&text=%D0%A4%D0%BE%D1%82%D0%BE+%D0%BE%D1%87%D1%96%D0%BA%D1%83%D1%94%D1%82%D1%8C%D1%81%D1%8F",
        "In_stock": "+",
        "Country": "Китай",
        "Quantity": 22
    },
    {
        "Brand": "Geely",
        "Model": "CK",
        "Articul": "E010000601",
        "Part_Name": "Клапан выпускной ",
        "Description": "Клапан выпускной ",
        "Price": 2,
        "Img": "https://dummyimage.com/640x480/2a2a2a/ffffff&text=%D0%A4%D0%BE%D1%82%D0%BE+%D0%BE%D1%87%D1%96%D0%BA%D1%83%D1%94%D1%82%D1%8C%D1%81%D1%8F",
        "In_stock": "+",
        "Country": "Китай",
        "Quantity": 9
    },
    {
        "Brand": "Geely",
        "Model": "CK",
        "Articul": 1403060180,
        "Part_Name": "Колодки задние (c abs)",
        "Description": "Колодки задние (c abs)",
        "Price": 8,
        "Img": "https://dummyimage.com/640x480/2a2a2a/ffffff&text=%D0%A4%D0%BE%D1%82%D0%BE+%D0%BE%D1%87%D1%96%D0%BA%D1%83%D1%94%D1%82%D1%8C%D1%81%D1%8F",
        "In_stock": "+",
        "Country": "Китай",
        "Quantity": 2
    },
    {
        "Brand": "Geely",
        "Model": "CK",
        "Articul": 3502145106,
        "Part_Name": "Колодки задние (без abs)",
        "Description": "Колодки задние (без abs)",
        "Price": 10,
        "Img": "https://dummyimage.com/640x480/2a2a2a/ffffff&text=%D0%A4%D0%BE%D1%82%D0%BE+%D0%BE%D1%87%D1%96%D0%BA%D1%83%D1%94%D1%82%D1%8C%D1%81%D1%8F",
        "In_stock": "+",
        "Country": "Китай",
        "Quantity": 6
    },
    {
        "Brand": "Geely",
        "Model": "CK",
        "Articul": "E100100005",
        "Part_Name": "Корзина сцепления",
        "Description": "Корзина сцепления",
        "Price": 20,
        "Img": "https://dummyimage.com/640x480/2a2a2a/ffffff&text=%D0%A4%D0%BE%D1%82%D0%BE+%D0%BE%D1%87%D1%96%D0%BA%D1%83%D1%94%D1%82%D1%8C%D1%81%D1%8F",
        "In_stock": "+",
        "Country": "Китай",
        "Quantity": 3
    },
    {
        "Brand": "Geely",
        "Model": "CK",
        "Articul": "E060000101",
        "Part_Name": "Патрубок термостата",
        "Description": "Патрубок термостата",
        "Price": 10,
        "Img": "https://dummyimage.com/640x480/2a2a2a/ffffff&text=%D0%A4%D0%BE%D1%82%D0%BE+%D0%BE%D1%87%D1%96%D0%BA%D1%83%D1%94%D1%82%D1%8C%D1%81%D1%8F",
        "In_stock": "+",
        "Country": "Китай",
        "Quantity": 2
    },
    {
        "Brand": "Geely",
        "Model": "CK",
        "Articul": 3401145106,
        "Part_Name": "Наконечник рулевой тяги левый",
        "Description": "Наконечник рулевой тяги левый",
        "Price": 3.0357142857142856,
        "Img": "https://dummyimage.com/640x480/2a2a2a/ffffff&text=%D0%A4%D0%BE%D1%82%D0%BE+%D0%BE%D1%87%D1%96%D0%BA%D1%83%D1%94%D1%82%D1%8C%D1%81%D1%8F",
        "In_stock": "+",
        "Country": "Китай",
        "Quantity": 4
    },
    {
        "Brand": "Geely",
        "Model": "CK",
        "Articul": 3401140106,
        "Part_Name": "Наконечник рулевой тяги правый",
        "Description": "Наконечник рулевой тяги правый",
        "Price": 3.0357142857142856,
        "Img": "https://dummyimage.com/640x480/2a2a2a/ffffff&text=%D0%A4%D0%BE%D1%82%D0%BE+%D0%BE%D1%87%D1%96%D0%BA%D1%83%D1%94%D1%82%D1%8C%D1%81%D1%8F",
        "In_stock": "+",
        "Country": "Китай",
        "Quantity": 4
    },
    {
        "Brand": "Geely",
        "Model": "CK",
        "Articul": "Е050100005",
        "Part_Name": "Насос водяной (помпа) (Meyle)",
        "Description": "Насос водяной (помпа) (Meyle)",
        "Price": 23,
        "Img": "https://dummyimage.com/640x480/2a2a2a/ffffff&text=%D0%A4%D0%BE%D1%82%D0%BE+%D0%BE%D1%87%D1%96%D0%BA%D1%83%D1%94%D1%82%D1%8C%D1%81%D1%8F",
        "In_stock": "+",
        "Country": "Китай",
        "Quantity": 1
    },
    {
        "Brand": "Geely",
        "Model": "CK",
        "Articul": "E040100005",
        "Part_Name": "Насос масла CK",
        "Description": "Насос масла CK",
        "Price": 17.857142857142858,
        "Img": "https://dummyimage.com/640x480/2a2a2a/ffffff&text=%D0%A4%D0%BE%D1%82%D0%BE+%D0%BE%D1%87%D1%96%D0%BA%D1%83%D1%94%D1%82%D1%8C%D1%81%D1%8F",
        "In_stock": "+",
        "Country": "Китай",
        "Quantity": 1
    },
    {
        "Brand": "Geely",
        "Model": "CK",
        "Articul": 1601285180,
        "Part_Name": "Насос топливный",
        "Description": "Насос топливный",
        "Price": 28.571428571428573,
        "Img": "https://dummyimage.com/640x480/2a2a2a/ffffff&text=%D0%A4%D0%BE%D1%82%D0%BE+%D0%BE%D1%87%D1%96%D0%BA%D1%83%D1%94%D1%82%D1%8C%D1%81%D1%8F",
        "In_stock": "+",
        "Country": "Китай",
        "Quantity": 1
    },
    {
        "Brand": "Geely",
        "Model": "CK",
        "Articul": 1400555180,
        "Part_Name": "Опора передней стойки",
        "Description": "Опора передней стойки",
        "Price": 7.142857142857143,
        "Img": "https://dummyimage.com/640x480/2a2a2a/ffffff&text=%D0%A4%D0%BE%D1%82%D0%BE+%D0%BE%D1%87%D1%96%D0%BA%D1%83%D1%94%D1%82%D1%8C%D1%81%D1%8F",
        "In_stock": "+",
        "Country": "Китай",
        "Quantity": 12
    },
    {
        "Brand": "Geely",
        "Model": "CK",
        "Articul": 1400621180,
        "Part_Name": "Отбойник с пыльником заднего амортизатора   ",
        "Description": "Отбойник с пыльником заднего амортизатора   ",
        "Price": 2,
        "Img": "https://dummyimage.com/640x480/2a2a2a/ffffff&text=%D0%A4%D0%BE%D1%82%D0%BE+%D0%BE%D1%87%D1%96%D0%BA%D1%83%D1%94%D1%82%D1%8C%D1%81%D1%8F",
        "In_stock": "+",
        "Country": "Китай",
        "Quantity": 2
    },
    {
        "Brand": "Geely",
        "Model": "CK",
        "Articul": 1400531180,
        "Part_Name": "Подшипник опорный передней стойки",
        "Description": "Подшипник опорный передней стойки",
        "Price": 2.6785714285714284,
        "Img": "https://dummyimage.com/640x480/2a2a2a/ffffff&text=%D0%A4%D0%BE%D1%82%D0%BE+%D0%BE%D1%87%D1%96%D0%BA%D1%83%D1%94%D1%82%D1%8C%D1%81%D1%8F",
        "In_stock": "+",
        "Country": "Китай",
        "Quantity": 14
    },
    {
        "Brand": "Geely",
        "Model": "CK",
        "Articul": "E020100106",
        "Part_Name": "Поршень CK",
        "Description": "Поршень CK",
        "Price": 30,
        "Img": "https://dummyimage.com/640x480/2a2a2a/ffffff&text=%D0%A4%D0%BE%D1%82%D0%BE+%D0%BE%D1%87%D1%96%D0%BA%D1%83%D1%94%D1%82%D1%8C%D1%81%D1%8F",
        "In_stock": "+",
        "Country": "Китай",
        "Quantity": 2
    },
    {
        "Brand": "Geely",
        "Model": "CK",
        "Articul": "E120200008",
        "Part_Name": "Провода свечные к-т",
        "Description": "Провода свечные к-т",
        "Price": 7,
        "Img": "https://dummyimage.com/640x480/2a2a2a/ffffff&text=%D0%A4%D0%BE%D1%82%D0%BE+%D0%BE%D1%87%D1%96%D0%BA%D1%83%D1%94%D1%82%D1%8C%D1%81%D1%8F",
        "In_stock": "+",
        "Country": "Китай",
        "Quantity": 3
    },
    {
        "Brand": "Geely",
        "Model": "CK",
        "Articul": "E010001601",
        "Part_Name": "Прокладка ГБЦ",
        "Description": "Прокладка ГБЦ",
        "Price": 2.5,
        "Img": "https://dummyimage.com/640x480/2a2a2a/ffffff&text=%D0%A4%D0%BE%D1%82%D0%BE+%D0%BE%D1%87%D1%96%D0%BA%D1%83%D1%94%D1%82%D1%8C%D1%81%D1%8F",
        "In_stock": "+",
        "Country": "Китай",
        "Quantity": 16
    },
    {
        "Brand": "Geely",
        "Model": "CK",
        "Articul": 1602028180,
        "Part_Name": "Прокладка глушителя СК",
        "Description": "Прокладка глушителя СК",
        "Price": 0.5,
        "Img": "https://dummyimage.com/640x480/2a2a2a/ffffff&text=%D0%A4%D0%BE%D1%82%D0%BE+%D0%BE%D1%87%D1%96%D0%BA%D1%83%D1%94%D1%82%D1%8C%D1%81%D1%8F",
        "In_stock": "+",
        "Country": "Китай",
        "Quantity": 13
    },
    {
        "Brand": "Geely",
        "Model": "CK",
        "Articul": "E010001501",
        "Part_Name": "Прокладка крышки клапанов",
        "Description": "Прокладка крышки клапанов",
        "Price": 3,
        "Img": "https://dummyimage.com/640x480/2a2a2a/ffffff&text=%D0%A4%D0%BE%D1%82%D0%BE+%D0%BE%D1%87%D1%96%D0%BA%D1%83%D1%94%D1%82%D1%8C%D1%81%D1%8F",
        "In_stock": "+",
        "Country": "Китай",
        "Quantity": 1
    },
    {
        "Brand": "Geely",
        "Model": "CK",
        "Articul": 1401106180,
        "Part_Name": "Пыльник гранаты внутренней",
        "Description": "Пыльник гранаты внутренней",
        "Price": 5,
        "Img": "https://dummyimage.com/640x480/2a2a2a/ffffff&text=%D0%A4%D0%BE%D1%82%D0%BE+%D0%BE%D1%87%D1%96%D0%BA%D1%83%D1%94%D1%82%D1%8C%D1%81%D1%8F",
        "In_stock": "+",
        "Country": "Китай",
        "Quantity": 7
    },
    {
        "Brand": "Geely",
        "Model": "CK",
        "Articul": 1400553180,
        "Part_Name": "Пыльник амортизатора переднего     ",
        "Description": "Пыльник амортизатора переднего     ",
        "Price": 2.75,
        "Img": "https://dummyimage.com/640x480/2a2a2a/ffffff&text=%D0%A4%D0%BE%D1%82%D0%BE+%D0%BE%D1%87%D1%96%D0%BA%D1%83%D1%94%D1%82%D1%8C%D1%81%D1%8F",
        "In_stock": "+",
        "Country": "Китай",
        "Quantity": 1
    },
    {
        "Brand": "Geely",
        "Model": "CK",
        "Articul": 2080000102,
        "Part_Name": "Реле втягивающее",
        "Description": "Реле втягивающее",
        "Price": 12.5,
        "Img": "https://dummyimage.com/640x480/2a2a2a/ffffff&text=%D0%A4%D0%BE%D1%82%D0%BE+%D0%BE%D1%87%D1%96%D0%BA%D1%83%D1%94%D1%82%D1%8C%D1%81%D1%8F",
        "In_stock": "+",
        "Country": "Китай",
        "Quantity": 1
    },
    {
        "Brand": "Geely",
        "Model": "CK",
        "Articul": "E030000401",
        "Part_Name": "Ремень генератора (5pk960)",
        "Description": "Ремень генератора (5pk960)",
        "Price": 3,
        "Img": "https://dummyimage.com/640x480/2a2a2a/ffffff&text=%D0%A4%D0%BE%D1%82%D0%BE+%D0%BE%D1%87%D1%96%D0%BA%D1%83%D1%94%D1%82%D1%8C%D1%81%D1%8F",
        "In_stock": "+",
        "Country": "Китай",
        "Quantity": 8
    },
    {
        "Brand": "Geely",
        "Model": "CK",
        "Articul": "E030000701",
        "Part_Name": "Ремень ГРМ",
        "Description": "Ремень ГРМ",
        "Price": 5,
        "Img": "https://dummyimage.com/640x480/2a2a2a/ffffff&text=%D0%A4%D0%BE%D1%82%D0%BE+%D0%BE%D1%87%D1%96%D0%BA%D1%83%D1%94%D1%82%D1%8C%D1%81%D1%8F",
        "In_stock": "+",
        "Country": "Китай",
        "Quantity": 1
    },
    {
        "Brand": "Geely",
        "Model": "CK",
        "Articul": 3412012105,
        "Part_Name": "Ремень ГУР (3pk510)",
        "Description": "Ремень ГУР (3pk510)",
        "Price": 2,
        "Img": "https://dummyimage.com/640x480/2a2a2a/ffffff&text=%D0%A4%D0%BE%D1%82%D0%BE+%D0%BE%D1%87%D1%96%D0%BA%D1%83%D1%94%D1%82%D1%8C%D1%81%D1%8F",
        "In_stock": "+",
        "Country": "Китай",
        "Quantity": 14
    },
    {
        "Brand": "Geely",
        "Model": "CK",
        "Articul": 1800183180,
        "Part_Name": "ремень кондиционера (4pk830)",
        "Description": "ремень кондиционера (4pk830)",
        "Price": 2,
        "Img": "https://dummyimage.com/640x480/2a2a2a/ffffff&text=%D0%A4%D0%BE%D1%82%D0%BE+%D0%BE%D1%87%D1%96%D0%BA%D1%83%D1%94%D1%82%D1%8C%D1%81%D1%8F",
        "In_stock": "+",
        "Country": "Китай",
        "Quantity": 2
    },
    {
        "Brand": "Geely",
        "Model": "CK",
        "Articul": 1801360180,
        "Part_Name": "Решетка радиатора",
        "Description": "Решетка радиатора",
        "Price": 11,
        "Img": "https://dummyimage.com/640x480/2a2a2a/ffffff&text=%D0%A4%D0%BE%D1%82%D0%BE+%D0%BE%D1%87%D1%96%D0%BA%D1%83%D1%94%D1%82%D1%8C%D1%81%D1%8F",
        "In_stock": "+",
        "Country": "Китай",
        "Quantity": 1
    },
    {
        "Brand": "Geely",
        "Model": "CK",
        "Articul": 1800706180,
        "Part_Name": "Ручка задней двери левая внутренняя (СК)  ",
        "Description": "Ручка задней двери левая внутренняя (СК)  ",
        "Price": 2,
        "Img": "https://dummyimage.com/640x480/2a2a2a/ffffff&text=%D0%A4%D0%BE%D1%82%D0%BE+%D0%BE%D1%87%D1%96%D0%BA%D1%83%D1%94%D1%82%D1%8C%D1%81%D1%8F",
        "In_stock": "+",
        "Country": "Китай",
        "Quantity": 2
    },
    {
        "Brand": "Geely",
        "Model": "CK",
        "Articul": 1800707180,
        "Part_Name": "Ручка задней двери правая внутренняя (СК)  ",
        "Description": "Ручка задней двери правая внутренняя (СК)  ",
        "Price": 2,
        "Img": "https://dummyimage.com/640x480/2a2a2a/ffffff&text=%D0%A4%D0%BE%D1%82%D0%BE+%D0%BE%D1%87%D1%96%D0%BA%D1%83%D1%94%D1%82%D1%8C%D1%81%D1%8F",
        "In_stock": "+",
        "Country": "Китай",
        "Quantity": 3
    },
    {
        "Brand": "Geely",
        "Model": "CK",
        "Articul": 1400607180,
        "Part_Name": "Рычаг поперечный передний задней подвески",
        "Description": "Рычаг поперечный передний задней подвески",
        "Price": 5.357142857142857,
        "Img": "https://dummyimage.com/640x480/2a2a2a/ffffff&text=%D0%A4%D0%BE%D1%82%D0%BE+%D0%BE%D1%87%D1%96%D0%BA%D1%83%D1%94%D1%82%D1%8C%D1%81%D1%8F",
        "In_stock": "+",
        "Country": "Китай",
        "Quantity": 5
    },
    {
        "Brand": "Geely",
        "Model": "CK",
        "Articul": 1400500180,
        "Part_Name": "Рычаг передний левый в сборе",
        "Description": "Рычаг передний левый в сборе",
        "Price": 20,
        "Img": "https://dummyimage.com/640x480/2a2a2a/ffffff&text=%D0%A4%D0%BE%D1%82%D0%BE+%D0%BE%D1%87%D1%96%D0%BA%D1%83%D1%94%D1%82%D1%8C%D1%81%D1%8F",
        "In_stock": "+",
        "Country": "Китай",
        "Quantity": 4
    },
    {
        "Brand": "Geely",
        "Model": "CK",
        "Articul": 1400501180,
        "Part_Name": "Рычаг передний правый в сборе",
        "Description": "Рычаг передний правый в сборе",
        "Price": 20,
        "Img": "https://dummyimage.com/640x480/2a2a2a/ffffff&text=%D0%A4%D0%BE%D1%82%D0%BE+%D0%BE%D1%87%D1%96%D0%BA%D1%83%D1%94%D1%82%D1%8C%D1%81%D1%8F",
        "In_stock": "+",
        "Country": "Китай",
        "Quantity": 3
    },
    {
        "Brand": "Geely",
        "Model": "CK",
        "Articul": 1400500180,
        "Part_Name": "Рычаг передний левый (без шаровой)",
        "Description": "Рычаг передний левый (без шаровой)",
        "Price": 16,
        "Img": "https://dummyimage.com/640x480/2a2a2a/ffffff&text=%D0%A4%D0%BE%D1%82%D0%BE+%D0%BE%D1%87%D1%96%D0%BA%D1%83%D1%94%D1%82%D1%8C%D1%81%D1%8F",
        "In_stock": "+",
        "Country": "Китай",
        "Quantity": 1
    },
    {
        "Brand": "Geely",
        "Model": "CK",
        "Articul": 1400501180,
        "Part_Name": "Рычаг передний правый (без шаровой)",
        "Description": "Рычаг передний правый (без шаровой)",
        "Price": 16,
        "Img": "https://dummyimage.com/640x480/2a2a2a/ffffff&text=%D0%A4%D0%BE%D1%82%D0%BE+%D0%BE%D1%87%D1%96%D0%BA%D1%83%D1%94%D1%82%D1%8C%D1%81%D1%8F",
        "In_stock": "+",
        "Country": "Китай",
        "Quantity": 1
    },
    {
        "Brand": "Geely",
        "Model": "CK",
        "Articul": 1014000504,
        "Part_Name": "Сайлентблок переднего рычага передний",
        "Description": "Сайлентблок переднего рычага передний",
        "Price": 1,
        "Img": "https://dummyimage.com/640x480/2a2a2a/ffffff&text=%D0%A4%D0%BE%D1%82%D0%BE+%D0%BE%D1%87%D1%96%D0%BA%D1%83%D1%94%D1%82%D1%8C%D1%81%D1%8F",
        "In_stock": "+",
        "Country": "Китай",
        "Quantity": 1
    },
    {
        "Brand": "Geely",
        "Model": "CK",
        "Articul": 1014000514,
        "Part_Name": "Сайлентблок переднего рычага задний правый(больш)",
        "Description": "Сайлентблок переднего рычага задний правый(больш)",
        "Price": 3,
        "Img": "https://dummyimage.com/640x480/2a2a2a/ffffff&text=%D0%A4%D0%BE%D1%82%D0%BE+%D0%BE%D1%87%D1%96%D0%BA%D1%83%D1%94%D1%82%D1%8C%D1%81%D1%8F",
        "In_stock": "+",
        "Country": "Китай",
        "Quantity": 2
    },
    {
        "Brand": "Geely",
        "Model": "CK",
        "Articul": 1014000515,
        "Part_Name": "Сайлентблок переднего рычага задний левый(больш)",
        "Description": "Сайлентблок переднего рычага задний левый(больш)",
        "Price": 3,
        "Img": "https://dummyimage.com/640x480/2a2a2a/ffffff&text=%D0%A4%D0%BE%D1%82%D0%BE+%D0%BE%D1%87%D1%96%D0%BA%D1%83%D1%94%D1%82%D1%8C%D1%81%D1%8F",
        "In_stock": "+",
        "Country": "Китай",
        "Quantity": 2
    },
    {
        "Brand": "Geely",
        "Model": "CK",
        "Articul": "E010510005",
        "Part_Name": "Сальник впускного клапана (к-т)",
        "Description": "Сальник впускного клапана (к-т)",
        "Price": 5,
        "Img": "https://dummyimage.com/640x480/2a2a2a/ffffff&text=%D0%A4%D0%BE%D1%82%D0%BE+%D0%BE%D1%87%D1%96%D0%BA%D1%83%D1%94%D1%82%D1%8C%D1%81%D1%8F",
        "In_stock": "+",
        "Country": "Китай",
        "Quantity": 50
    },
    {
        "Brand": "Geely",
        "Model": "CK",
        "Articul": "E040110005",
        "Part_Name": "Сальник коленвала передний",
        "Description": "Сальник коленвала передний",
        "Price": 2,
        "Img": "https://dummyimage.com/640x480/2a2a2a/ffffff&text=%D0%A4%D0%BE%D1%82%D0%BE+%D0%BE%D1%87%D1%96%D0%BA%D1%83%D1%94%D1%82%D1%8C%D1%81%D1%8F",
        "In_stock": "+",
        "Country": "Китай",
        "Quantity": 3
    },
    {
        "Brand": "Geely",
        "Model": "CK",
        "Articul": "E020510005",
        "Part_Name": "Сальник коленвала задний",
        "Description": "Сальник коленвала задний",
        "Price": 2,
        "Img": "https://dummyimage.com/640x480/2a2a2a/ffffff&text=%D0%A4%D0%BE%D1%82%D0%BE+%D0%BE%D1%87%D1%96%D0%BA%D1%83%D1%94%D1%82%D1%8C%D1%81%D1%8F",
        "In_stock": "+",
        "Country": "Китай",
        "Quantity": 2
    },
    {
        "Brand": "Geely",
        "Model": "CK",
        "Articul": 2400111101,
        "Part_Name": "Сальник внутренний задней цапфы",
        "Description": "Сальник внутренний задней цапфы",
        "Price": 1,
        "Img": "https://dummyimage.com/640x480/2a2a2a/ffffff&text=%D0%A4%D0%BE%D1%82%D0%BE+%D0%BE%D1%87%D1%96%D0%BA%D1%83%D1%94%D1%82%D1%8C%D1%81%D1%8F",
        "In_stock": "+",
        "Country": "Китай",
        "Quantity": 12
    },
    {
        "Brand": "Geely",
        "Model": "CK",
        "Articul": 3170103001,
        "Part_Name": "Сальник первичного вала КПП(заглушки торцевой) СК",
        "Description": "Сальник первичного вала КПП(заглушки торцевой) СК",
        "Price": 2,
        "Img": "https://dummyimage.com/640x480/2a2a2a/ffffff&text=%D0%A4%D0%BE%D1%82%D0%BE+%D0%BE%D1%87%D1%96%D0%BA%D1%83%D1%94%D1%82%D1%8C%D1%81%D1%8F",
        "In_stock": "+",
        "Country": "Китай",
        "Quantity": 4
    },
    {
        "Brand": "Geely",
        "Model": "CK",
        "Articul": 1400631180,
        "Part_Name": "Стойка стабилизатора задняя",
        "Description": "Стойка стабилизатора задняя",
        "Price": 1.4285714285714286,
        "Img": "https://dummyimage.com/640x480/2a2a2a/ffffff&text=%D0%A4%D0%BE%D1%82%D0%BE+%D0%BE%D1%87%D1%96%D0%BA%D1%83%D1%94%D1%82%D1%8C%D1%81%D1%8F",
        "In_stock": "+",
        "Country": "Китай",
        "Quantity": 25
    },
    {
        "Brand": "Geely",
        "Model": "CK",
        "Articul": 1400509180,
        "Part_Name": "Стойка стабилизатора передняя левая",
        "Description": "Стойка стабилизатора передняя левая",
        "Price": 3,
        "Img": "https://dummyimage.com/640x480/2a2a2a/ffffff&text=%D0%A4%D0%BE%D1%82%D0%BE+%D0%BE%D1%87%D1%96%D0%BA%D1%83%D1%94%D1%82%D1%8C%D1%81%D1%8F",
        "In_stock": "+",
        "Country": "Китай",
        "Quantity": 6
    },
    {
        "Brand": "Geely",
        "Model": "CK",
        "Articul": 1400551180,
        "Part_Name": "Стойка стабилизатора передняя правая",
        "Description": "Стойка стабилизатора передняя правая",
        "Price": 3,
        "Img": "https://dummyimage.com/640x480/2a2a2a/ffffff&text=%D0%A4%D0%BE%D1%82%D0%BE+%D0%BE%D1%87%D1%96%D0%BA%D1%83%D1%94%D1%82%D1%8C%D1%81%D1%8F",
        "In_stock": "+",
        "Country": "Китай",
        "Quantity": 1
    },
    {
        "Brand": "Geely",
        "Model": "CK",
        "Articul": 1402137180,
        "Part_Name": "Суппорт тормозной правый(c ABS) СК",
        "Description": "Суппорт тормозной правый(c ABS) СК",
        "Price": 20,
        "Img": "https://dummyimage.com/640x480/2a2a2a/ffffff&text=%D0%A4%D0%BE%D1%82%D0%BE+%D0%BE%D1%87%D1%96%D0%BA%D1%83%D1%94%D1%82%D1%8C%D1%81%D1%8F",
        "In_stock": "+",
        "Country": "Китай",
        "Quantity": 1
    },
    {
        "Brand": "Geely",
        "Model": "CK",
        "Articul": 1407041180,
        "Part_Name": "Трос тормоза ручного левый ",
        "Description": "Трос тормоза ручного левый ",
        "Price": 4,
        "Img": "https://dummyimage.com/640x480/2a2a2a/ffffff&text=%D0%A4%D0%BE%D1%82%D0%BE+%D0%BE%D1%87%D1%96%D0%BA%D1%83%D1%94%D1%82%D1%8C%D1%81%D1%8F",
        "In_stock": "+",
        "Country": "Китай",
        "Quantity": 1
    },
    {
        "Brand": "Geely",
        "Model": "CK",
        "Articul": 1407042180,
        "Part_Name": "Трос тормоза ручного правый",
        "Description": "Трос тормоза ручного правый",
        "Price": 4,
        "Img": "https://dummyimage.com/640x480/2a2a2a/ffffff&text=%D0%A4%D0%BE%D1%82%D0%BE+%D0%BE%D1%87%D1%96%D0%BA%D1%83%D1%94%D1%82%D1%8C%D1%81%D1%8F",
        "In_stock": "+",
        "Country": "Китай",
        "Quantity": 1
    },
    {
        "Brand": "Geely",
        "Model": "CK",
        "Articul": 3401505106,
        "Part_Name": "Тяга рулевая",
        "Description": "Тяга рулевая",
        "Price": 5,
        "Img": "https://dummyimage.com/640x480/2a2a2a/ffffff&text=%D0%A4%D0%BE%D1%82%D0%BE+%D0%BE%D1%87%D1%96%D0%BA%D1%83%D1%94%D1%82%D1%8C%D1%81%D1%8F",
        "In_stock": "+",
        "Country": "Китай",
        "Quantity": 9
    },
    {
        "Brand": "Geely",
        "Model": "CK",
        "Articul": 1701051180,
        "Part_Name": "Фара передняя левая (без корректора)",
        "Description": "Фара передняя левая (без корректора)",
        "Price": 39,
        "Img": "https://dummyimage.com/640x480/2a2a2a/ffffff&text=%D0%A4%D0%BE%D1%82%D0%BE+%D0%BE%D1%87%D1%96%D0%BA%D1%83%D1%94%D1%82%D1%8C%D1%81%D1%8F",
        "In_stock": "+",
        "Country": "Китай",
        "Quantity": 3
    },
    {
        "Brand": "Geely",
        "Model": "CK",
        "Articul": 1017001076,
        "Part_Name": "Фара передняя левая (с корректором)",
        "Description": "Фара передняя левая (с корректором)",
        "Price": 50,
        "Img": "https://dummyimage.com/640x480/2a2a2a/ffffff&text=%D0%A4%D0%BE%D1%82%D0%BE+%D0%BE%D1%87%D1%96%D0%BA%D1%83%D1%94%D1%82%D1%8C%D1%81%D1%8F",
        "In_stock": "+",
        "Country": "Китай",
        "Quantity": 1
    },
    {
        "Brand": "Geely",
        "Model": "CK",
        "Articul": "1701052180 ",
        "Part_Name": "Фара передняя правая (без корректора)",
        "Description": "Фара передняя правая (без корректора)",
        "Price": 39,
        "Img": "https://dummyimage.com/640x480/2a2a2a/ffffff&text=%D0%A4%D0%BE%D1%82%D0%BE+%D0%BE%D1%87%D1%96%D0%BA%D1%83%D1%94%D1%82%D1%8C%D1%81%D1%8F",
        "In_stock": "+",
        "Country": "Китай",
        "Quantity": 2
    },
    {
        "Brand": "Geely",
        "Model": "CK",
        "Articul": 1701221180,
        "Part_Name": "Фара противотуманная передняя левая",
        "Description": "Фара противотуманная передняя левая",
        "Price": 5,
        "Img": "https://dummyimage.com/640x480/2a2a2a/ffffff&text=%D0%A4%D0%BE%D1%82%D0%BE+%D0%BE%D1%87%D1%96%D0%BA%D1%83%D1%94%D1%82%D1%8C%D1%81%D1%8F",
        "In_stock": "+",
        "Country": "Китай",
        "Quantity": 4
    },
    {
        "Brand": "Geely",
        "Model": "CK",
        "Articul": 1109140005,
        "Part_Name": "Фильтр воздушный",
        "Description": "Фильтр воздушный",
        "Price": 2,
        "Img": "https://dummyimage.com/640x480/2a2a2a/ffffff&text=%D0%A4%D0%BE%D1%82%D0%BE+%D0%BE%D1%87%D1%96%D0%BA%D1%83%D1%94%D1%82%D1%8C%D1%81%D1%8F",
        "In_stock": "+",
        "Country": "Китай",
        "Quantity": 2
    },
    {
        "Brand": "Geely",
        "Model": "CK",
        "Articul": 1601255180,
        "Part_Name": "Фильтр топливный",
        "Description": "Фильтр топливный",
        "Price": 2,
        "Img": "https://dummyimage.com/640x480/2a2a2a/ffffff&text=%D0%A4%D0%BE%D1%82%D0%BE+%D0%BE%D1%87%D1%96%D0%BA%D1%83%D1%94%D1%82%D1%8C%D1%81%D1%8F",
        "In_stock": "+",
        "Country": "Китай",
        "Quantity": 37
    },
    {
        "Brand": "Geely",
        "Model": "CK",
        "Articul": 1701551180,
        "Part_Name": "Фонарь задний левый",
        "Description": "Фонарь задний левый",
        "Price": 17,
        "Img": "https://dummyimage.com/640x480/2a2a2a/ffffff&text=%D0%A4%D0%BE%D1%82%D0%BE+%D0%BE%D1%87%D1%96%D0%BA%D1%83%D1%94%D1%82%D1%8C%D1%81%D1%8F",
        "In_stock": "+",
        "Country": "Китай",
        "Quantity": 1
    },
    {
        "Brand": "Geely",
        "Model": "CK",
        "Articul": 1701552180,
        "Part_Name": "Фонарь задний правый",
        "Description": "Фонарь задний правый",
        "Price": 17,
        "Img": "https://dummyimage.com/640x480/2a2a2a/ffffff&text=%D0%A4%D0%BE%D1%82%D0%BE+%D0%BE%D1%87%D1%96%D0%BA%D1%83%D1%94%D1%82%D1%8C%D1%81%D1%8F",
        "In_stock": "+",
        "Country": "Китай",
        "Quantity": 1
    },
    {
        "Brand": "Geely",
        "Model": "CK",
        "Articul": 3502135005,
        "Part_Name": "цилиндр задний  тормозной левый (с abs)",
        "Description": "цилиндр задний  тормозной левый (с abs)",
        "Price": 4,
        "Img": "https://dummyimage.com/640x480/2a2a2a/ffffff&text=%D0%A4%D0%BE%D1%82%D0%BE+%D0%BE%D1%87%D1%96%D0%BA%D1%83%D1%94%D1%82%D1%8C%D1%81%D1%8F",
        "In_stock": "+",
        "Country": "Китай",
        "Quantity": 3
    },
    {
        "Brand": "Geely",
        "Model": "CK",
        "Articul": 3502140005,
        "Part_Name": "цилиндр задний  тормозной правый (с abs)",
        "Description": "цилиндр задний  тормозной правый (с abs)",
        "Price": 4,
        "Img": "https://dummyimage.com/640x480/2a2a2a/ffffff&text=%D0%A4%D0%BE%D1%82%D0%BE+%D0%BE%D1%87%D1%96%D0%BA%D1%83%D1%94%D1%82%D1%8C%D1%81%D1%8F",
        "In_stock": "+",
        "Country": "Китай",
        "Quantity": 1
    },
    {
        "Brand": "Geely",
        "Model": "CK",
        "Articul": 1402280025,
        "Part_Name": "Цилиндр сцепления главный ",
        "Description": "Цилиндр сцепления главный ",
        "Price": 11,
        "Img": "https://dummyimage.com/640x480/2a2a2a/ffffff&text=%D0%A4%D0%BE%D1%82%D0%BE+%D0%BE%D1%87%D1%96%D0%BA%D1%83%D1%94%D1%82%D1%8C%D1%81%D1%8F",
        "In_stock": "+",
        "Country": "Китай",
        "Quantity": 1
    },
    {
        "Brand": "Geely",
        "Model": "CK",
        "Articul": 1406115180,
        "Part_Name": "Шланг тормозной задний     ",
        "Description": "Шланг тормозной задний     ",
        "Price": 2.5,
        "Img": "https://dummyimage.com/640x480/2a2a2a/ffffff&text=%D0%A4%D0%BE%D1%82%D0%BE+%D0%BE%D1%87%D1%96%D0%BA%D1%83%D1%94%D1%82%D1%8C%D1%81%D1%8F",
        "In_stock": "+",
        "Country": "Китай",
        "Quantity": 1
    },
    {
        "Brand": "Geely",
        "Model": "CK",
        "Articul": 1401101180,
        "Part_Name": "Шрус наружный 1.5 c ABS(z23)",
        "Description": "Шрус наружный 1.5 c ABS(z23)",
        "Price": 20,
        "Img": "https://dummyimage.com/640x480/2a2a2a/ffffff&text=%D0%A4%D0%BE%D1%82%D0%BE+%D0%BE%D1%87%D1%96%D0%BA%D1%83%D1%94%D1%82%D1%8C%D1%81%D1%8F",
        "In_stock": "+",
        "Country": "Китай",
        "Quantity": 1
    },
    {
        "Brand": "Geely",
        "Model": "CK",
        "Articul": "1401101180-01",
        "Part_Name": "Шрус наружный 1.5 c ABS(z30)",
        "Description": "Шрус наружный 1.5 c ABS(z30)",
        "Price": 20,
        "Img": "https://dummyimage.com/640x480/2a2a2a/ffffff&text=%D0%A4%D0%BE%D1%82%D0%BE+%D0%BE%D1%87%D1%96%D0%BA%D1%83%D1%94%D1%82%D1%8C%D1%81%D1%8F",
        "In_stock": "+",
        "Country": "Китай",
        "Quantity": 4
    },
    {
        "Brand": "Geely",
        "Model": "CK",
        "Articul": 1401102180,
        "Part_Name": "Шрус внутренний 1.5 c ABS",
        "Description": "Шрус внутренний 1.5 c ABS",
        "Price": 20,
        "Img": "https://dummyimage.com/640x480/2a2a2a/ffffff&text=%D0%A4%D0%BE%D1%82%D0%BE+%D0%BE%D1%87%D1%96%D0%BA%D1%83%D1%94%D1%82%D1%8C%D1%81%D1%8F",
        "In_stock": "+",
        "Country": "Китай",
        "Quantity": 1
    }
]